makerchip/__init__.py
makerchip/__main__.py
makerchip/_vendor/__init__.py
makerchip/_vendor/native_web_app.py
makerchip/asset/default.tlv
makerchip_app-1.1.5.dist-info/LICENSE.md
makerchip_app-1.1.5.dist-info/METADATA
makerchip_app-1.1.5.dist-info/WHEEL
makerchip_app-1.1.5.dist-info/entry_points.txt
makerchip_app-1.1.5.dist-info/top_level.txt
makerchip_app-1.1.5.dist-info/RECORD
