Metadata-Version: 2.1
Name: makerchip-app
Version: 1.1.5
Summary: Makerchip desktop app
Home-page: https://gitlab.com/rweda/makerchip-app
Author: Redwood EDA
Author-email: makerchip-app@redwoodeda.com
License: UNKNOWN
Platform: UNKNOWN
Classifier: Topic :: Text Editors :: Integrated Development Environments (IDE)
Classifier: License :: OSI Approved :: MIT License
Requires-Python: >=3.6
Requires-Dist: click
Requires-Dist: requests
Requires-Dist: sseclient-py
